cloud_api_signer/__init__.py
cloud_api_signer/bce.py
cloud_api_signer/models.py
cloud_api_signer/utils.py
cloud_api_signer/volc.py
cloud_api_signer-0.4.0.dist-info/LICENSE
cloud_api_signer-0.4.0.dist-info/METADATA
cloud_api_signer-0.4.0.dist-info/WHEEL
cloud_api_signer-0.4.0.dist-info/RECORD
