Metadata-Version: 2.1
Name: cloud-api-signer
Version: 0.4.0
Summary: 
Author: Huang Shaoyan
Author-email: huangshaoyan1982@gmail.com
Requires-Python: >=3.8.19,<4.0.0
Classifier: Programming Language :: Python :: 3
Classifier: Programming Language :: Python :: 3.9
Classifier: Programming Language :: Python :: 3.10
Classifier: Programming Language :: Python :: 3.11
Classifier: Programming Language :: Python :: 3.12
Requires-Dist: pydantic (>=2)
